rmnest/__init__.py
rmnest/app.py
rmnest/fit_RM.py
rmnest/likelihood.py
rmnest/model.py
rmnest/utils.py
rmnest-0.3.1.dist-info/LICENSE
rmnest-0.3.1.dist-info/METADATA
rmnest-0.3.1.dist-info/WHEEL
rmnest-0.3.1.dist-info/entry_points.txt
rmnest-0.3.1.dist-info/top_level.txt
rmnest-0.3.1.dist-info/RECORD
