Metadata-Version: 2.1
Name: rmnest
Version: 0.3.1
Summary: Faraday rotation measurement for pulsars and FRBs
Home-page: https://github.com/mlower/rmnest
Author: Marcus Lower
Author-email: marcus.lower@csiro.au
License: MIT
Classifier: Operating System :: OS Independent
Classifier: License :: OSI Approved :: MIT License
Classifier: Programming Language :: Python :: 3 :: Only
Classifier: Programming Language :: Python :: 3.7
Classifier: Programming Language :: Python :: 3.8
Classifier: Programming Language :: Python :: 3.9
Classifier: Intended Audience :: Science/Research
Classifier: Topic :: Scientific/Engineering :: Astronomy
Requires-Python: >=3.7
License-File: LICENSE
Requires-Dist: future
Requires-Dist: numpy
Requires-Dist: scipy
Requires-Dist: matplotlib
Requires-Dist: bilby
Requires-Dist: uncertainties
Requires-Dist: importlib-metadata
Provides-Extra: tests
Requires-Dist: pytest ; extra == 'tests'
Requires-Dist: pytest-cov ; extra == 'tests'
